setup.py
CsuPMTD.egg-info/PKG-INFO
CsuPMTD.egg-info/SOURCES.txt
CsuPMTD.egg-info/dependency_links.txt
CsuPMTD.egg-info/requires.txt
CsuPMTD.egg-info/top_level.txt
PMTD/__init__.py
PMTD/model.py
PMTD/maskrcnn_benchmark/_C.cpython-36m-x86_64-linux-gnu.so
PMTD/maskrcnn_benchmark/__init__.py
PMTD/maskrcnn_benchmark/apex/__init__.py
PMTD/maskrcnn_benchmark/apex/setup.py
PMTD/maskrcnn_benchmark/apex/apex/__init__.py
PMTD/maskrcnn_benchmark/apex/apex/RNN/RNNBackend.py
PMTD/maskrcnn_benchmark/apex/apex/RNN/__init__.py
PMTD/maskrcnn_benchmark/apex/apex/RNN/cells.py
PMTD/maskrcnn_benchmark/apex/apex/RNN/models.py
PMTD/maskrcnn_benchmark/apex/apex/amp/__init__.py
PMTD/maskrcnn_benchmark/apex/apex/amp/__version__.py
PMTD/maskrcnn_benchmark/apex/apex/amp/_amp_state.py
PMTD/maskrcnn_benchmark/apex/apex/amp/_initialize.py
PMTD/maskrcnn_benchmark/apex/apex/amp/_process_optimizer.py
PMTD/maskrcnn_benchmark/apex/apex/amp/amp.py
PMTD/maskrcnn_benchmark/apex/apex/amp/compat.py
PMTD/maskrcnn_benchmark/apex/apex/amp/frontend.py
PMTD/maskrcnn_benchmark/apex/apex/amp/handle.py
PMTD/maskrcnn_benchmark/apex/apex/amp/opt.py
PMTD/maskrcnn_benchmark/apex/apex/amp/rnn_compat.py
PMTD/maskrcnn_benchmark/apex/apex/amp/scaler.py
PMTD/maskrcnn_benchmark/apex/apex/amp/utils.py
PMTD/maskrcnn_benchmark/apex/apex/amp/wrap.py
PMTD/maskrcnn_benchmark/apex/apex/amp/lists/__init__.py
PMTD/maskrcnn_benchmark/apex/apex/amp/lists/functional_overrides.py
PMTD/maskrcnn_benchmark/apex/apex/amp/lists/tensor_overrides.py
PMTD/maskrcnn_benchmark/apex/apex/amp/lists/torch_overrides.py
PMTD/maskrcnn_benchmark/apex/apex/contrib/__init__.py
PMTD/maskrcnn_benchmark/apex/apex/contrib/examples/__init__.py
PMTD/maskrcnn_benchmark/apex/apex/contrib/examples/multihead_attn/__init__.py
PMTD/maskrcnn_benchmark/apex/apex/contrib/examples/multihead_attn/func_test_multihead_attn.py
PMTD/maskrcnn_benchmark/apex/apex/contrib/examples/multihead_attn/perf_test_multihead_attn.py
PMTD/maskrcnn_benchmark/apex/apex/contrib/groupbn/__init__.py
PMTD/maskrcnn_benchmark/apex/apex/contrib/groupbn/batch_norm.py
PMTD/maskrcnn_benchmark/apex/apex/contrib/multihead_attn/__init__.py
