Metadata-Version: 1.0
Name: CsuPMTD
Version: 1.0.27
Summary: word
Home-page: UNKNOWN
Author: csu_ywj
Author-email: UNKNOWN
License: MIT Licence
Keywords: pip
Platform: any
